htr_pipeline/__init__.py
htr_pipeline/models/detector.onnx
htr_pipeline/models/reader.json
htr_pipeline/models/reader.onnx
htr_pipeline/reader/__init__.py
htr_pipeline/reader/ctc.py
htr_pipeline/word_detector/__init__.py
htr_pipeline/word_detector/aabb.py
htr_pipeline/word_detector/aabb_clustering.py
htr_pipeline/word_detector/coding.py
htr_pipeline/word_detector/iou.py
easyhtr-0.1.1.dist-info/METADATA
easyhtr-0.1.1.dist-info/WHEEL
easyhtr-0.1.1.dist-info/top_level.txt
easyhtr-0.1.1.dist-info/RECORD
